waxdispatcherhelper/__init__.py
waxdispatcherhelper/waxdispatcherhelper.py
waxdispatcherhelper-0.0.1.dist-info/METADATA
waxdispatcherhelper-0.0.1.dist-info/WHEEL
waxdispatcherhelper-0.0.1.dist-info/top_level.txt
waxdispatcherhelper-0.0.1.dist-info/RECORD
